nuqql_matrixd/__init__.py
nuqql_matrixd/client.py
nuqql_matrixd/main.py
nuqql_matrixd/matrix.py
nuqql_matrixd/server.py
nuqql_matrixd-0.6.0.dist-info/LICENSE
nuqql_matrixd-0.6.0.dist-info/METADATA
nuqql_matrixd-0.6.0.dist-info/WHEEL
nuqql_matrixd-0.6.0.dist-info/entry_points.txt
nuqql_matrixd-0.6.0.dist-info/top_level.txt
nuqql_matrixd-0.6.0.dist-info/RECORD
