Metadata-Version: 2.1
Name: nuqql-matrixd
Version: 0.6.0
Summary: Matrix client network daemon using the Matrix Python SDK
Home-page: https://github.com/hwipl/nuqql-matrixd
Author: hwipl
Author-email: nuqql-matrixd@hwipl.net
License: MIT
Platform: UNKNOWN
Classifier: Programming Language :: Python :: 3
Classifier: License :: OSI Approved :: MIT License
Requires-Python: >=3.7
License-File: LICENSE
Requires-Dist: nuqql-based (~=0.3.0)
Requires-Dist: matrix-client (~=0.4.0)
